marimo_magic/__init__.py
marimo_magic/magic.py
marimo_magic-1.0.0.dist-info/METADATA
marimo_magic-1.0.0.dist-info/WHEEL
marimo_magic-1.0.0.dist-info/licenses/LICENSE
marimo_magic-1.0.0.dist-info/RECORD
