Metadata-Version: 2.4
Name: marimo-magic
Version: 1.0.0
Summary: IPython magic command for embedding marimo notebooks in Jupyter/Colab
Project-URL: Homepage, https://github.com/hublot-io/marimo-magic
Project-URL: Repository, https://github.com/hublot-io/marimo-magic.git
Project-URL: Issues, https://github.com/hublot-io/marimo-magic/issues
Author: Nathan
License-Expression: MIT
License-File: LICENSE
Keywords: colab,interactive,ipython,jupyter,magic,marimo,notebook
Classifier: Development Status :: 5 - Production/Stable
Classifier: Framework :: IPython
Classifier: Framework :: Jupyter
Classifier: Intended Audience :: Developers
Classifier: Intended Audience :: Science/Research
Classifier: License :: OSI Approved :: MIT License
Classifier: Operating System :: OS Independent
Classifier: Programming Language :: Python :: 3
Classifier: Programming Language :: Python :: 3.8
Classifier: Programming Language :: Python :: 3.9
Classifier: Programming Language :: Python :: 3.10
Classifier: Programming Language :: Python :: 3.11
Classifier: Programming Language :: Python :: 3.12
Classifier: Topic :: Scientific/Engineering
Classifier: Topic :: Software Development :: Libraries :: Python Modules
Requires-Python: >=3.8
Requires-Dist: ipython>=7.0.0
Requires-Dist: requests>=2.20.0
Provides-Extra: dev
Requires-Dist: black; extra == 'dev'
Requires-Dist: flake8; extra == 'dev'
Requires-Dist: isort; extra == 'dev'
Requires-Dist: pytest>=6.0; extra == 'dev'
